hypermax/__init__.py
hypermax/cli.py
hypermax/configuration.py
hypermax/cui.py
hypermax/execution.py
hypermax/file_utils.py
hypermax/hyperparameter.py
hypermax/optimizer.py
hypermax/results_analyzer.py
hypermax/test_model.py
hypermax/utils.py
hypermax/algorithms/__init__.py
hypermax/algorithms/adaptive_bayesian_hyperband_optimizer.py
hypermax/algorithms/atpe_optimizer.py
hypermax/algorithms/human_guided_optimizer_wrapper.py
hypermax/algorithms/optimization_algorithm_base.py
hypermax/algorithms/random_search_optimizer.py
hypermax/algorithms/tpe_optimizer.py
hypermax/atpe_models/model-gamma-configuration.json
hypermax/atpe_models/model-gamma.txt
hypermax/atpe_models/model-nEICandidates-configuration.json
hypermax/atpe_models/model-nEICandidates.txt
hypermax/atpe_models/model-resultFilteringAgeMultiplier-configuration.json
hypermax/atpe_models/model-resultFilteringAgeMultiplier.txt
hypermax/atpe_models/model-resultFilteringLossRankMultiplier-configuration.json
hypermax/atpe_models/model-resultFilteringLossRankMultiplier.txt
hypermax/atpe_models/model-resultFilteringMode-configuration.json
hypermax/atpe_models/model-resultFilteringMode.txt
hypermax/atpe_models/model-resultFilteringRandomProbability-configuration.json
hypermax/atpe_models/model-resultFilteringRandomProbability.txt
hypermax/atpe_models/model-secondaryCorrelationExponent-configuration.json
hypermax/atpe_models/model-secondaryCorrelationExponent.txt
hypermax/atpe_models/model-secondaryCorrelationMultiplier-configuration.json
hypermax/atpe_models/model-secondaryCorrelationMultiplier.txt
hypermax/atpe_models/model-secondaryCutoff-configuration.json
hypermax/atpe_models/model-secondaryCutoff.txt
hypermax/atpe_models/model-secondaryFixedProbability-configuration.json
hypermax/atpe_models/model-secondaryFixedProbability.txt
hypermax/atpe_models/model-secondaryLockingMode-configuration.json
hypermax/atpe_models/model-secondaryLockingMode.txt
hypermax/atpe_models/model-secondaryProbabilityMode-configuration.json
hypermax-0.5.1.dist-info/LICENSE
hypermax-0.5.1.dist-info/METADATA
hypermax-0.5.1.dist-info/WHEEL
hypermax-0.5.1.dist-info/entry_points.txt
hypermax-0.5.1.dist-info/top_level.txt
hypermax-0.5.1.dist-info/RECORD
