Metadata-Version: 2.1
Name: hypermax
Version: 0.5.1
Summary: Better, faster hyperparameter optimization by mixing the best of humans and machines.
Home-page: https://github.com/electricbrainio/hypermax
Author: Bradley Arsenault (Electric Brain)
Author-email: brad@electricbrain.io
License: MIT
Platform: Linux
Platform: OS-X
Classifier: Intended Audience :: Education
Classifier: Intended Audience :: Science/Research
Classifier: Intended Audience :: Developers
Classifier: Environment :: Console
Classifier: License :: OSI Approved :: BSD License
Classifier: Operating System :: MacOS :: MacOS X
Classifier: Operating System :: POSIX
Classifier: Operating System :: Unix
Classifier: Programming Language :: Python
Classifier: Programming Language :: Python :: 3
Classifier: Topic :: Scientific/Engineering
Classifier: Topic :: Software Development
Requires-Python: >=3
Requires-Dist: hyperopt
Requires-Dist: scikit-learn
Requires-Dist: numpy
Requires-Dist: scipy
Requires-Dist: jsonschema
Requires-Dist: pyyaml
Requires-Dist: urwid
Requires-Dist: panwid (==0.2.5)
Requires-Dist: lightgbm
Requires-Dist: psutil
Requires-Dist: matplotlib
Requires-Dist: colors.py
Requires-Dist: pymongo
